auto_mode/__init__.py
auto_mode/main.py
auto_mode/suntime.py
auto_mode-1.0.2.dist-info/entry_points.txt
auto_mode-1.0.2.dist-info/WHEEL
auto_mode-1.0.2.dist-info/METADATA
auto_mode-1.0.2.dist-info/RECORD
